webcface/__init__.py
webcface/canvas2d.py
webcface/canvas2d_base.py
webcface/canvas3d.py
webcface/canvas3d_base.py
webcface/client.py
webcface/client_data.py
webcface/client_impl.py
webcface/components.py
webcface/field.py
webcface/func.py
webcface/func_info.py
webcface/func_listener.py
webcface/geometries.py
webcface/image.py
webcface/image_frame.py
webcface/log.py
webcface/log_handler.py
webcface/member.py
webcface/message.py
webcface/py.typed
webcface/temporal_component.py
webcface/text.py
webcface/transform.py
webcface/transform_impl.py
webcface/typing.py
webcface/value.py
webcface/view.py
webcface/view_base.py
webcface-3.1.0.dist-info/LICENSE
webcface-3.1.0.dist-info/METADATA
webcface-3.1.0.dist-info/WHEEL
webcface-3.1.0.dist-info/RECORD
