Metadata-Version: 2.3
Name: webcface
Version: 3.1.0
Summary: WebCFace Client for Python
License: MIT
Author: na-trium-144
Author-email: 100704180+na-trium-144@users.noreply.github.com
Requires-Python: >=3.6,<4.0
Classifier: License :: OSI Approved :: MIT License
Classifier: Programming Language :: Python :: 3
Classifier: Programming Language :: Python :: 3.6
Classifier: Programming Language :: Python :: 3.7
Classifier: Programming Language :: Python :: 3.8
Classifier: Programming Language :: Python :: 3.9
Classifier: Programming Language :: Python :: 3.10
Classifier: Programming Language :: Python :: 3.11
Classifier: Programming Language :: Python :: 3.12
Classifier: Programming Language :: Python :: 3.13
Requires-Dist: importlib-metadata (>=1) ; python_version < "3.8"
Requires-Dist: u-msgpack-python (>=2,<3)
Requires-Dist: websocket-client (>=1,<2)
Project-URL: Documentation, https://na-trium-144.github.io/webcface-python/
Project-URL: Repository, https://github.com/na-trium-144/webcface-python
